Metadata-Version: 2.1
Name: i-upload
Version: 0.5
Summary: an upload software
Author: jack
Author-email: kinginjack@gmail.com
License: GPL-3.0
Platform: UNKNOWN
Requires-Python: >=3.8
